closek/__init__.py
closek/closek.py
closek/version.py
closek-1.1.dist-info/LICENSE
closek-1.1.dist-info/METADATA
closek-1.1.dist-info/WHEEL
closek-1.1.dist-info/top_level.txt
closek-1.1.dist-info/RECORD
