Metadata-Version: 2.1
Name: closek
Version: 1.1
Summary: Scikit-learn-style implementation of the close-k classifier.
Home-page: https://github.com/bryan-he/close-k
Author: Bryan He
Author-email: bryanhe@stanford.edu
License: UNKNOWN
Platform: UNKNOWN
Classifier: Programming Language :: Python :: 3
Classifier: License :: OSI Approved :: MIT License
Requires-Dist: torch
Requires-Dist: numpy
Requires-Dist: sklearn
